crypto_history/__init__.py
crypto_history/data_container/__init__.py
crypto_history/data_container/data_container_access.py
crypto_history/data_container/data_container_post.py
crypto_history/data_container/data_container_pre.py
crypto_history/data_container/utilities.py
crypto_history/emit_data/__init__.py
crypto_history/emit_data/save_to_disk.py
crypto_history/stock_market/__init__.py
crypto_history/stock_market/request.py
crypto_history/stock_market/stock_market_factory.py
crypto_history/stock_market/tickers.py
crypto_history/utilities/__init__.py
crypto_history/utilities/datetime_operations.py
crypto_history/utilities/exceptions.py
crypto_history/utilities/general_utilities.py
crypto_history-1.2b12.dist-info/LICENSE
crypto_history-1.2b12.dist-info/WHEEL
crypto_history-1.2b12.dist-info/METADATA
crypto_history-1.2b12.dist-info/RECORD
